{
  "nameOnPage": "Katrina Bouchard",
  "researchClassification": [
    "Clinical sexology",
    "Mental health and wellbeing",
    "Sexual identy, sexual attraction and sexual behaviour"
  ],
  "interests": [
    "Sexual health",
    "sexual response",
    "sexual well-being",
    "women's health",
    "couples"
  ],
  "affiliations": [
    "Women's Health Research Institute"
  ],
  "researchOptions": [
    "I am available and interested in collaborations (e.g. clusters, grants).",
    "I am interested in and conduct interdisciplinary research.",
    "I am interested in working with undergraduate students on research projects."
  ]
}