{
  "nameOnPage": "Enda Murphy",
  "researchClassification": [
    "Hydraulic engineering",
    "Marine engineering, n.e.c.",
    "Nearshore processes and coastal oceanography",
    "Estuarine oceanography"
  ],
  "interests": [
    "Coastal and estuarine system dynamics",
    "Nature-based solutions",
    "Whole system thinking",
    "Coastal systems engineering",
    "Transdisciplinary research",
    "Numerical modelling",
    "Physical modelling",
    "Coastal flood and erosion hazard risk"
  ],
  "affiliations": [
    "Centre for Climate Justice",
    "Climate Change Health Effects, Adaptation, and ResiLience (HEAL)",
    "Disaster Resilience Research Network",
    "Enhancing Ecosystem Sustainability",
    "Institute for Resources, Environment and Sustainability",
    "Institute for the Oceans and Fisheries",
    "Marine Systems Research Cluster"
  ],
  "researchOptions": [
    "I am available and interested in collaborations (e.g. clusters, grants).",
    "I am interested in and conduct interdisciplinary research.",
    "I am interested in working with undergraduate students on research projects."
  ]
}